askai/.version
askai/__classpath__.py
askai/__init__.py
askai/__main__.py
askai/welcome.txt
askai/core/__init__.py
askai/core/askai.py
askai/core/askai_cli.py
askai/core/askai_configs.py
askai/core/askai_events.py
askai/core/askai_messages.py
askai/core/askai_prompt.py
askai/core/askai_settings.py
askai/core/commander/__init__.py
askai/core/commander/commander.py
askai/core/commander/commands/__init__.py
askai/core/commander/commands/cache_cmd.py
askai/core/commander/commands/camera_cmd.py
askai/core/commander/commands/general_cmd.py
askai/core/commander/commands/history_cmd.py
askai/core/commander/commands/settings_cmd.py
askai/core/commander/commands/tts_stt_cmd.py
askai/core/component/__init__.py
askai/core/component/cache_service.py
askai/core/component/geo_location.py
askai/core/component/image_store.py
askai/core/component/internet_service.py
askai/core/component/rag_provider.py
askai/core/component/scheduler.py
askai/core/component/summarizer.py
askai/core/component/text_streamer.py
askai/core/component/multimedia/__init__.py
askai/core/component/multimedia/audio_player.py
askai/core/component/multimedia/camera.py
askai/core/component/multimedia/recorder.py
askai/core/engine/__init__.py
askai/core/engine/ai_engine.py
askai/core/engine/ai_model.py
askai/core/engine/ai_vision.py
askai/core/engine/engine_factory.py
askai/core/engine/openai/__init__.py
askai/core/engine/openai/openai_configs.py
askai/core/engine/openai/openai_engine.py
askai/core/engine/openai/openai_model.py
askai/core/engine/openai/openai_vision.py
askai/core/engine/openai/temperature.py
askai/core/enums/__init__.py
askai/core/enums/acc_color.py
askai/core/enums/response_model.py
askai/core/enums/router_mode.py
askai/core/enums/run_modes.py
askai/core/enums/verbosity.py
askai/core/model/__init__.py
askai/core/model/acc_response.py
askai/core/model/action_plan.py
askai/core/model/ai_reply.py
askai/core/model/api_keys.py
askai/core/model/image_result.py
askai/core/model/model_result.py
hspylib_askai-1.2.19.dist-info/METADATA
hspylib_askai-1.2.19.dist-info/WHEEL
hspylib_askai-1.2.19.dist-info/top_level.txt
hspylib_askai-1.2.19.dist-info/RECORD
