Metadata-Version: 2.4
Name: hspylib-askai
Version: 1.2.19
Summary: HomeSetup - AskAI
Home-page: https://github.com/yorevs/hspylib
Author: Hugo Saporetti Junior
Author-email: yorevs@hotmail.com
License: MIT
Project-URL: GitHub, https://github.com/yorevs/hspylib
Project-URL: PyPi, https://pypi.org/project/hspylib-askai/
Keywords: ai,openai,application,generative,ask,terminal,ai-terminal-integration
Platform: Darwin
Platform: Linux
Classifier: License :: OSI Approved :: MIT License
Classifier: Programming Language :: Python :: 3.10
Classifier: Operating System :: MacOS :: MacOS X
Classifier: Operating System :: POSIX :: Linux
Classifier: Operating System :: Unix
Classifier: Development Status :: 3 - Alpha
Classifier: Environment :: Console
Classifier: Natural Language :: English
Classifier: Topic :: Terminals
Classifier: Intended Audience :: Developers
Requires-Python: >=3.10
Requires-Dist: hspylib>=1.12.53
Requires-Dist: hspylib-datasource>=0.9.82
Requires-Dist: hspylib-clitt>=0.9.145
Requires-Dist: hspylib-setman>=0.10.43
Requires-Dist: retry2>=0.9.5
Requires-Dist: pause>=0.3
Requires-Dist: tqdm>=4.67.1
Requires-Dist: pyperclip>=1.11.0
Requires-Dist: python-magic>=0.4.27
Requires-Dist: pytz>=2025.2
Requires-Dist: transitions>=0.9.3
Requires-Dist: pydantic>=2.12.4
Requires-Dist: cryptography>=46.0.3
Requires-Dist: langchain==1.1.0
Requires-Dist: langchain-openai==1.1.0
Requires-Dist: langchain-community==0.4.1
Requires-Dist: langchain-google-community==3.0.1
Requires-Dist: langchain_classic==1.0.0
Requires-Dist: openai-whisper==20250625
Requires-Dist: openai==2.8.1
Requires-Dist: google-api-python-client==2.187.0
Requires-Dist: google-search-results==2.4.2
Requires-Dist: fake_useragent~=2.2.0
Requires-Dist: requests~=2.32.5
Requires-Dist: urllib3~=2.5.0
Requires-Dist: aiohttp~=3.13.1
Requires-Dist: html2text~=2025.4.15
Requires-Dist: rich>=14.2.0
Requires-Dist: textual>=6.6.0
Requires-Dist: soundfile==0.13.1
Requires-Dist: PyAudio==0.2.14
Requires-Dist: SpeechRecognition==3.14.4
Requires-Dist: opencv-python==4.12.0.88
Requires-Dist: pyautogui==0.9.54
Requires-Dist: torch~=2.8.0
Requires-Dist: torchvision~=0.23.0
Requires-Dist: open-clip-torch
Requires-Dist: opentelemetry-api~=1.36.0
Requires-Dist: opentelemetry-sdk~=1.36.0
Requires-Dist: opentelemetry-proto~=1.36.0
Requires-Dist: opentelemetry-semantic-conventions~=0.48b0
Requires-Dist: opentelemetry-instrumentation-fastapi~=0.48b0
Requires-Dist: opentelemetry-instrumentation-asgi~=0.48b0
Requires-Dist: transformers~=4.57.3
Requires-Dist: unstructured~=0.18.21
Requires-Dist: unstructured[md]~=0.18.21
Requires-Dist: tiktoken~=0.12.0
Requires-Dist: nltk~=3.9.2
Requires-Dist: tokenizers~=0.22.1
Requires-Dist: faiss-cpu~=1.13.0
Requires-Dist: chromadb~=1.3.5
Requires-Dist: deepl==1.25.0
Requires-Dist: argostranslate==1.10.0
Dynamic: author
Dynamic: author-email
Dynamic: classifier
Dynamic: description
Dynamic: description-content-type
Dynamic: home-page
Dynamic: keywords
Dynamic: license
Dynamic: platform
Dynamic: project-url
Dynamic: requires-dist
Dynamic: requires-python
Dynamic: summary
